{
  "title": "Wells Fargo’s Mike Mayo: Citi My Top Pick of Big Banks",
  "link": "https://www.bloomberg.com/news/videos/2026-07-13/wells-fargo-s-mike-mayo-citi-my-top-pick-of-big-banks-video",
  "summary": "Investors are preparing for a significant earnings week as five of the six largest US banks, including JPMorgan, Citi, Wells Fargo, Bank of America, and Goldman Sachs, are scheduled to report their quarterly results within a few hours of each other. Mike Mayo, Head of US Large-Cap Bank Research at Wells Fargo, joined the program to share his outlook. He expects overall bank earnings to increase by 15 to 20 percent year-over-year, driven by a combination of strong Wall Street trading revenues and",
  "published": "Mon, 13 Jul 2026 21:47:45 GMT",
  "source": "bloomberg"
}